{
  "sources": [
    {
      "title": "Twitter @DeFi Airdrops 🦇🔊",
      "feedUrl": "https://rsshub.app/twitter/user/defi_airdrops",
      "siteUrl": "https://twitter.com/defi_airdrops",
      "articles": [
        {
          "id": "https://twitter.com/defi_airdrops/status/1664449967015211008",
          "author": "DeFi Airdrops 🦇🔊",
          "description": "Re This is just chapter 1 so they will probably add more initiatives.\nStay tuned. \nAnd join our telegram to always stay up to date.\nhttps://t.me/+Stjobn_4QE1h2xCm",
          "link": "https://twitter.com/defi_airdrops/status/1664449967015211008",
          "publishedOn": "2023-06-02T01:52:50.000Z",
          "wordCount": null,
          "title": "Re This is just chapter 1 so they will probably add more initiatives. Stay tuned. And join our telegram to always stay up to date. https://t.me/+Stjob...",
          "imageUrl": null
        },
        {
          "id": "https://twitter.com/defi_airdrops/status/1664449964838354944",
          "author": "DeFi Airdrops 🦇🔊",
          "description": "Re Pearl points are updated every week based on how much you stake and will be redeemable against $SWELL at TGE.\nThey also set  some collective milestone targets that when hit, will give everyone more $SWELL.\nThe target is 50k $ETH and it seems like they're halfway there. https://t.co/iYhgoSAOJE",
          "link": "https://twitter.com/defi_airdrops/status/1664449964838354944",
          "publishedOn": "2023-06-02T01:52:50.000Z",
          "wordCount": null,
          "title": "Re Pearl points are updated every week based on how much you stake and will be redeemable against $SWELL at TGE. They also set some collective milesto...",
          "imageUrl": null
        },
        {
          "id": "https://twitter.com/defi_airdrops/status/1664449961747189760",
          "author": "DeFi Airdrops 🦇🔊",
          "description": "Re To kick off their growth they have launched an initiative called Voyage.\nEarly adopters earn PEARLS for staking $ETH -> $swETH.\nOr providing liquidity on $swETH- $ETH pairs on protocols like @mavprotocol @AuraFinance & @Timeless_Fi. https://t.co/cjsA63PdI0",
          "link": "https://twitter.com/defi_airdrops/status/1664449961747189760",
          "publishedOn": "2023-06-02T01:52:49.000Z",
          "wordCount": null,
          "title": "Re To kick off their growth they have launched an initiative called Voyage. Early adopters earn PEARLS for staking $ETH -> $swETH. Or providing liquid...",
          "imageUrl": null
        },
        {
          "id": "https://twitter.com/defi_airdrops/status/1664449959213809664",
          "author": "DeFi Airdrops 🦇🔊",
          "description": "Re First off some stats.\nAudited by Sigma Prime (top auditor) and bounty program on @immunefi.\n$35m TVL and growing.\nThe investors 👇 https://t.co/zJVYcPGdW0",
          "link": "https://twitter.com/defi_airdrops/status/1664449959213809664",
          "publishedOn": "2023-06-02T01:52:48.000Z",
          "wordCount": null,
          "title": "Re First off some stats. Audited by Sigma Prime (top auditor) and bounty program on @immunefi. $35m TVL and growing. The investors 👇 https://t.co/z...",
          "imageUrl": null
        },
        {
          "id": "https://twitter.com/defi_airdrops/status/1664449956646903808",
          "author": "DeFi Airdrops 🦇🔊",
          "description": "🚨 $SWELL AIRDROP CONFIRMED🚨\n@swellnetworkio is making serious moves in the liquid staking space with their 0% commission rate yielding stakers a 5% apr.\nThey've announced a 5% of token supply airdrop to early stakers joining their Voyage.\nMore on Voyage 👇 https://t.co/yM6acYgZ0a",
          "link": "https://twitter.com/defi_airdrops/status/1664449956646903808",
          "publishedOn": "2023-06-02T01:52:48.000Z",
          "wordCount": null,
          "title": "🚨 $SWELL AIRDROP CONFIRMED🚨 @swellnetworkio is making serious moves in the liquid staking space with their 0% commission rate yielding stakers a...",
          "imageUrl": null
        },
        {
          "id": "https://twitter.com/defi_airdrops/status/1664094947199578112",
          "author": "DeFi Airdrops 🦇🔊",
          "description": "Re Best way to qualify for this potential airdrop is to take a loan out against one of your NFT's:\nMAYC\n@Azuki\n@pudgypenguins\n@BEANZOfficial\n@moonbirds\nCloneX\n@BoredApeYC\n@doodles\n@CryptoDickbutts\n@miladymaker\nChromie Squiggle\n@DeGodsNFT \nRates are low & you cant get liquidated.",
          "link": "https://twitter.com/defi_airdrops/status/1664094947199578112",
          "publishedOn": "2023-06-01T02:22:07.000Z",
          "wordCount": null,
          "title": "Re Best way to qualify for this potential airdrop is to take a loan out against one of your NFT's: MAYC @Azuki @pudgypenguins @BEANZOfficial @moonbird...",
          "imageUrl": null
        },
        {
          "id": "https://twitter.com/defi_airdrops/status/1664094350656286720",
          "author": "DeFi Airdrops 🦇🔊",
          "description": "Re Link: https://astaria.xyz/",
          "link": "https://twitter.com/defi_airdrops/status/1664094350656286720",
          "publishedOn": "2023-06-01T02:19:45.000Z",
          "wordCount": null,
          "title": "Re Link: https://astaria.xyz/",
          "imageUrl": null
        },
        {
          "id": "https://twitter.com/defi_airdrops/status/1664094181206425600",
          "author": "DeFi Airdrops 🦇🔊",
          "description": "Re Early adopters receive a fun meme token created by Joe a long time ago\nBut pretty sure they will launch a token eventually and reward early adopters in more substantial ways.\nhttps://twitter.com/AstariaXYZ/status/1664006408847732739?s=20\n\nAstaria: Starting today we are distributing $LSD to each new 7 day loan on Astaria\nMAYC\n@Azuki\n@pudgypenguins\n@BEANZOfficial\n@moonbirds\nCloneX\n@BoredApeYC\n@doodles\n@CryptoDickbutts\n@miladymaker\nChromie Squiggle\n@DeGodsNFT \n$LSD is burnable for physical paper\nhttps://astaria.xyz/borrow/loans/new https://t.co/V1p6kmLJ9i",
          "link": "https://twitter.com/defi_airdrops/status/1664094181206425600",
          "publishedOn": "2023-06-01T02:19:04.000Z",
          "wordCount": null,
          "title": "Re Early adopters receive a fun meme token created by Joe a long time ago But pretty sure they will launch a token eventually and reward early adopter...",
          "imageUrl": null
        },
        {
          "id": "https://twitter.com/defi_airdrops/status/1664093921335726080",
          "author": "DeFi Airdrops 🦇🔊",
          "description": "🚨 NEW HIGH-POTENTIAL PROTOCOL🚨\n@AstariaXYZ is a new NFT lending platform by ex-Sushi CTO @josephdelong \nIt allows loan underwriters like @UpshotHQ @deepnftvaluebot (or anyone else) to create loan offer pools.\nYou can then accept these offers and lend your NFTs for $ETH.\n\nAstaria: We are celebrating the launch of @DeGodsNFT loans on Astaria today 🎉\nBorrow up to 5 ETH for 30 days @ 1% APR\n-Instant liquidity\n-Fixed terms + no liquidations \n-Best rates on Degods anywhere (+ only pay for the time accrued)\nHedge risk for 1% APR\nhttps://astaria.xyz/borrow/loans/new https://t.co/RvD4WJZZtA",
          "link": "https://twitter.com/defi_airdrops/status/1664093921335726080",
          "publishedOn": "2023-06-01T02:18:02.000Z",
          "wordCount": null,
          "title": "🚨 NEW HIGH-POTENTIAL PROTOCOL🚨 @AstariaXYZ is a new NFT lending platform by ex-Sushi CTO @josephdelong It allows loan underwriters like @UpshotH...",
          "imageUrl": null
        },
        {
          "id": "https://twitter.com/defi_airdrops/status/1660797079936172033",
          "author": "DeFi Airdrops 🦇🔊",
          "description": "Re Full list of addresses: https://raw.githubusercontent.com/PikaProtocol/PikaTGEWhitelist/master/TGEWhitelist?token=GHSAT0AAAAAABS33UNNEJLQDCSJRANVOW22ZDDQGUA",
          "link": "https://twitter.com/defi_airdrops/status/1660797079936172033",
          "publishedOn": "2023-05-22T23:57:34.000Z",
          "wordCount": null,
          "title": "Re Full list of addresses: https://raw.githubusercontent.com/PikaProtocol/PikaTGEWhitelist/master/TGEWhitelist?token=GHSAT0AAAAAABS33UNNEJLQDCSJRANVOW...",
          "imageUrl": null
        },
        {
          "id": "https://twitter.com/defi_airdrops/status/1660797076517818368",
          "author": "DeFi Airdrops 🦇🔊",
          "description": "The $PIKA TGE is happening today at 14:00 UTC\nIf you used Pika before you can invest in Phase I of the TGE @ 37m market cap.\nYour allocation will be 1-5 ETH based on your usage (addresses below 👇)\nThese addresses will also receive an airdrop later but locked tokens $esPIKA 🪂 https://t.co/eRsksZy5Gm\n\n\nDeFi Airdrops 🦇🔊: 🚨 $PIKA AIRDROP CONFIRMED 🚨\nGood news for everyone who followed our call and traded or LP'd on @PikaProtocol\nWhitelisted users who interacted with the protocol will be able to particpate in their public sale @ 37m mkt cap\n+ mention retroactive airdrop\nhttps://twitter.com/PikaProtocol/status/1655895942602838018?s=20 https://t.co/X6iNvIWW1h",
          "link": "https://twitter.com/defi_airdrops/status/1660797076517818368",
          "publishedOn": "2023-05-22T23:57:33.000Z",
          "wordCount": null,
          "title": "The $PIKA TGE is happening today at 14:00 UTC If you used Pika before you can invest in Phase I of the TGE @ 37m market cap. Your allocation will be 1...",
          "imageUrl": null
        }
      ]
    }
  ],
  "cliVersion": "1.15.1"
}